{"animations":[{"name":"p_rest_spine","property":"rotation","framePerSecond":100,"dataType":1,"loopBehavior":2,"blendingSpeed":0.01,"keys":[{"frame":0,"values":[0.38746309394274114,0,0,null,[-0.003909537524467298,0,0]]},{"frame":50,"values":[0.19198621771937624,0,0,[0.0025651514538590488,0,0],[0.01905539621283877,0,0]]},{"frame":100,"values":[0.38746309394274114,0,0,[0.003909537524467298,0,0]]}],"ranges":[]},{"name":"p_rest_neck","property":"rotation","framePerSecond":100,"dataType":1,"loopBehavior":2,"blendingSpeed":0.01,"keys":[{"frame":0,"values":[-0.2617993877991494,-0.593411945678072,0.19896753472735357]}],"ranges":[]},{"name":"p_rest_left_shoulder","property":"rotation","framePerSecond":100,"dataType":1,"loopBehavior":1,"blendingSpeed":0.01,"keys":[{"frame":0,"values":[-1.2217304763960306,2.161939344445376,3.0543261909900767]},{"frame":50,"values":[-1.2217304763960306,2.161939344445376,3.0543261909900767]},{"frame":100,"values":[-1.2217304763960306,2.161939344445376,3.0543261909900767]}],"ranges":[]},{"name":"p_rest_left_arm","property":"rotation","framePerSecond":100,"dataType":1,"loopBehavior":1,"blendingSpeed":0.01,"keys":[{"frame":0,"values":[0.7382742735936013,2.293362637120549,-0.41887902047863906]},{"frame":50,"values":[0.4084070449666731,2.443460952792061,-0.3490658503988659]},{"frame":100,"values":[0.7382742735936013,2.293362637120549,-0.41887902047863906]}],"ranges":[]},{"name":"p_rest_left_forearm","property":"rotation","framePerSecond":100,"dataType":1,"loopBehavior":1,"blendingSpeed":0.01,"keys":[{"frame":0,"values":[0.7703883318302971,0.13439035240356337,0.28797932657906433]},{"frame":50,"values":[0.7703883318302971,0.13439035240356337,0.28797932657906433]},{"frame":100,"values":[0.7703883318302971,0.13439035240356337,0.28797932657906433]}],"ranges":[]},{"name":"p_rest_left_hand","property":"rotation","framePerSecond":100,"dataType":1,"loopBehavior":1,"blendingSpeed":0.01,"keys":[{"frame":0,"values":[0.19198621771937624,1.4398966328953218,0.19896753472735357]},{"frame":50,"values":[0.19198621771937624,1.4398966328953218,0.19896753472735357]},{"frame":100,"values":[0.19198621771937624,1.4398966328953218,0.19896753472735357]}],"ranges":[]},{"name":"p_rest_right_shoulder","property":"rotation","framePerSecond":100,"dataType":1,"loopBehavior":1,"blendingSpeed":0.01,"keys":[{"frame":0,"values":[0.9075712110370513,2.234021442552742,-2.5953045977155678]},{"frame":50,"values":[0.9075712110370513,2.234021442552742,-2.5953045977155678]},{"frame":100,"values":[0.9075712110370513,2.234021442552742,-2.5953045977155678]}],"ranges":[]},{"name":"p_rest_right_arm","property":"rotation","framePerSecond":100,"dataType":1,"loopBehavior":1,"blendingSpeed":0.01,"keys":[{"frame":0,"values":[0.10471975511965977,-2.5830872929516078,0.03490658503988659]}],"ranges":[]},{"name":"p_rest_right_forearm","property":"rotation","framePerSecond":100,"dataType":1,"loopBehavior":1,"blendingSpeed":0.01,"keys":[{"frame":0,"values":[-0.1117010721276371,0.6440264939859075,1.1205013797803596]},{"frame":50,"values":[-0.1117010721276371,0.6440264939859075,1.1205013797803596]},{"frame":100,"values":[-0.1117010721276371,0.6440264939859075,1.1205013797803596]}],"ranges":[]},{"name":"p_rest_right_handthumb","property":"rotation","framePerSecond":100,"dataType":1,"loopBehavior":1,"blendingSpeed":0.01,"keys":[{"frame":0,"values":[-0.9337511498169663,-0.03490658503988659,0.06283185307179587]},{"frame":50,"values":[-0.9337511498169663,-0.03490658503988659,0.06283185307179587]},{"frame":100,"values":[-0.9337511498169663,-0.03490658503988659,0.06283185307179587]}],"ranges":[]},{"name":"p_rest_up_left_leg","property":"rotation","framePerSecond":100,"dataType":1,"loopBehavior":2,"blendingSpeed":0.01,"keys":[{"frame":0,"values":[0.43,2.8244734112594014,3.0841560757293336]},{"frame":38,"values":[1.4390601848139037,2.7843552880748828,3.092066740849872]},{"frame":73,"values":[-0.88,2.7843552880748828,3.092066740849872]},{"frame":100,"values":[0.43,2.7843552880748828,3.092066740849872]}],"ranges":[]},{"name":"p_rest_up_right_leg","property":"rotation","framePerSecond":100,"dataType":1,"loopBehavior":2,"blendingSpeed":0.01,"keys":[{"frame":0,"values":[1.4486232791552935,2.8623399732707004,-2.7576202181510405]}],"ranges":[]},{"name":"p_rest_hips_ctrl","property":"rotation","framePerSecond":100,"dataType":1,"loopBehavior":2,"blendingSpeed":0.01,"keys":[{"frame":0,"values":[-0.03490658503988659,-3.141592653589793,-3.141592653589793]}],"ranges":[]},{"name":"p_rest_hips","property":"rotation","framePerSecond":100,"dataType":1,"loopBehavior":2,"blendingSpeed":0.01,"keys":[{"frame":0,"values":[0,2.6878070480712672,-3.141592653589793]}],"ranges":[]},{"name":"p_rest_left_leg","property":"rotation","framePerSecond":100,"dataType":1,"loopBehavior":2,"blendingSpeed":0.01,"keys":[{"frame":0,"values":[1.0192722831646883,2.7576202181510405,2.6738444140553126]}],"ranges":[]},{"name":"p_rest_right_leg","property":"rotation","framePerSecond":100,"dataType":1,"loopBehavior":2,"blendingSpeed":0.01,"keys":[{"frame":0,"values":[0.7021459580773187,0,-0.0942477796076938]}],"ranges":[]},{"name":"p_rest_left_foot","property":"rotation","framePerSecond":100,"dataType":1,"loopBehavior":2,"blendingSpeed":0.01,"keys":[{"frame":0,"values":[-71,71,-52]}],"ranges":[]},{"name":"p_rest_toes","property":"rotation","framePerSecond":100,"dataType":1,"loopBehavior":2,"blendingSpeed":0.01,"keys":[{"frame":0,"values":[0.43,3,0]}],"ranges":[]},{"name":"p_rest_toes","property":"rotation","framePerSecond":100,"dataType":1,"loopBehavior":2,"blendingSpeed":0.01,"keys":[{"frame":0,"values":[0.43,3,0]}],"ranges":[]}]}